[{"id":1,"rango":"0 a 4 a\u00f1os","Hombres":94523,"Mujeres":93370,"total":187893},{"id":2,"rango":"10 a 14 a\u00f1os","Hombres":100847,"Mujeres":97754,"total":198601},{"id":3,"rango":"15 a 19 a\u00f1os","Hombres":99841,"Mujeres":98300,"total":198141},{"id":4,"rango":"20 a 24 a\u00f1os","Hombres":104347,"Mujeres":104692,"total":209039},{"id":5,"rango":"25 a 29 a\u00f1os","Hombres":105543,"Mujeres":108596,"total":214139},{"id":6,"rango":"30 a 34 a\u00f1os","Hombres":94293,"Mujeres":100283,"total":194576},{"id":7,"rango":"35 a 39 a\u00f1os","Hombres":87967,"Mujeres":94776,"total":182743},{"id":8,"rango":"40 a 44 a\u00f1os","Hombres":79318,"Mujeres":86410,"total":165728},{"id":9,"rango":"45 a 49 a\u00f1os","Hombres":71841,"Mujeres":77991,"total":149832},{"id":10,"rango":"5 a 9 a\u00f1os","Hombres":99958,"Mujeres":97011,"total":196969},{"id":11,"rango":"50 a 54 a\u00f1os","Hombres":59009,"Mujeres":66848,"total":125857},{"id":12,"rango":"55 a 59 a\u00f1os","Hombres":46132,"Mujeres":51771,"total":97903},{"id":13,"rango":"60 a 64 a\u00f1os","Hombres":37769,"Mujeres":42960,"total":80729},{"id":14,"rango":"65 a 69 a\u00f1os","Hombres":26736,"Mujeres":31097,"total":57833},{"id":15,"rango":"70 a 74 a\u00f1os","Hombres":18799,"Mujeres":22180,"total":40979},{"id":16,"rango":"75 a 79 a\u00f1os","Hombres":12516,"Mujeres":14901,"total":27417},{"id":17,"rango":"80 a 84 a\u00f1os","Hombres":7578,"Mujeres":9743,"total":17321},{"id":18,"rango":"85 a\u00f1os o m\u00e1s","Hombres":6403,"Mujeres":9540,"total":15943}]