{"0":{"segmento":"A","M\u00ednimo":"$8,043.48","M\u00e1ximo":"$29,919.38","Promedio":"$18,091.71"},"1":{"segmento":"B","M\u00ednimo":"$107.25","M\u00e1ximo":"$26,616.67","Promedio":"$16,086.00"},"2":{"segmento":"C","M\u00ednimo":"$3,358.64","M\u00e1ximo":"$21,018.69","Promedio":"$14,335.25"},"3":{"segmento":"D","M\u00ednimo":"$2,400.66","M\u00e1ximo":"$19,200.00","Promedio":"$12,598.32"},"4":{"segmento":"E","M\u00ednimo":"$63.06","M\u00e1ximo":"$15,833.33","Promedio":"$8,092.55"},"5":{"segmento":"L","M\u00ednimo":"$17,375.00","M\u00e1ximo":"$42,500.00","Promedio":"$30,200.68"},"6":{"segmento":"S","M\u00ednimo":"$1,973.68","M\u00e1ximo":"$33,475.70","Promedio":"$19,329.26"},"7":{"segmento":"general","M\u00ednimo":"$63.06","M\u00e1ximo":"$28,767.87","Promedio":"$15,340.44"}}